{
  "id": "diversao-animais-em-reuniao",
  "title": "Animais em Reuniao",
  "description": "Cenarios corporativos com fauna organizada.",
  "category": "Diversao",
  "tags": [
    "animais",
    "trabalho",
    "humor",
    "colecao-diversao",
    "serie-22"
  ],
  "questions": {
    "q1": "Qual momento marcou sua relacao com o tema animais em reuniao?",
    "q2": "O que mais surpreende voce quando pensa em animais em reuniao?",
    "q3": "Que lembranca sua combina demais com animais em reuniao?",
    "q4": "Se voce tivesse que resumir animais em reuniao em uma frase, qual seria?",
    "q5": "Qual lado pouco falado de animais em reuniao mais chama sua atencao?",
    "q6": "Que experiencia boa voce associa imediatamente a animais em reuniao?",
    "q7": "Que erro comum as pessoas cometem quando falam de animais em reuniao?",
    "q8": "O que voce gostaria de viver mais dentro de animais em reuniao?",
    "q9": "Qual conversa sincera sobre animais em reuniao vale a pena ter mais vezes?",
    "q10": "Que habito ou atitude melhora muito qualquer experiencia ligada a animais em reuniao?",
    "q11": "Quando animais em reuniao funciona muito bem para voce?",
    "q12": "Quando animais em reuniao fica mais dificil do que deveria?",
    "q13": "Que tipo de pessoa costuma combinar com o clima de animais em reuniao?",
    "q14": "Que historia engraçada voce poderia contar sobre animais em reuniao?",
    "q15": "Que historia profunda voce poderia contar sobre animais em reuniao?",
    "q16": "Qual expectativa sobre animais em reuniao voce ja mudou com o tempo?",
    "q17": "Que conselho sincero voce daria para alguem vivendo animais em reuniao hoje?",
    "q18": "Que pergunta sobre animais em reuniao quase ninguem faz e deveria fazer?",
    "q19": "O que faz voce confiar mais em alguem dentro de animais em reuniao?",
    "q20": "O que faz voce perder o interesse em animais em reuniao?",
    "q21": "Que detalhe simples torna animais em reuniao melhor?",
    "q22": "Que exagero costuma atrapalhar animais em reuniao?",
    "q23": "Se pudesse ajustar uma regra invisivel sobre animais em reuniao, qual seria?",
    "q24": "Que sinal mostra que animais em reuniao esta indo na direcao certa?",
    "q25": "Que sinal mostra que animais em reuniao precisa ser revisto?",
    "q26": "Que aprendizado recente mudou sua visao sobre animais em reuniao?",
    "q27": "Que dificuldade voce encara de forma mais leve hoje em animais em reuniao?",
    "q28": "Qual escolha pequena gera grande impacto em animais em reuniao?",
    "q29": "Se animais em reuniao virasse um filme, que genero seria?",
    "q30": "Se animais em reuniao tivesse trilha sonora, como ela seria?",
    "q31": "Que personagem real ou ficticio representaria bem animais em reuniao?",
    "q32": "Qual parte de animais em reuniao voce protege com mais cuidado?",
    "q33": "Qual parte de animais em reuniao merece mais espontaneidade?",
    "q34": "Que limite faz bem quando o assunto e animais em reuniao?",
    "q35": "Que risco vale a pena correr em animais em reuniao?",
    "q36": "Que risco nao compensa correr em animais em reuniao?",
    "q37": "O que seria uma versao mais madura de animais em reuniao para voce?",
    "q38": "O que seria uma versao mais divertida de animais em reuniao para voce?",
    "q39": "Que combinacao improvavel melhoraria animais em reuniao?",
    "q40": "Que comparacao ajuda a explicar animais em reuniao para outra pessoa?",
    "q41": "O que costuma ser mais importante do que parece em animais em reuniao?",
    "q42": "O que costuma parecer importante e no fim nao e tanto em animais em reuniao?",
    "q43": "Que memoria antiga ainda influencia sua visao sobre animais em reuniao?",
    "q44": "Que desejo futuro aparece quando voce pensa em animais em reuniao?",
    "q45": "O que voce faria diferente se pudesse recomecar em animais em reuniao?",
    "q46": "O que vale repetir porque sempre funciona em animais em reuniao?",
    "q47": "Que conversa pendente combinaria com o tema animais em reuniao?",
    "q48": "Qual foi sua maior descoberta pessoal ligada a animais em reuniao?",
    "q49": "Que atitude alheia faz voce admirar mais alguem em animais em reuniao?",
    "q50": "Que atitude alheia faz voce se afastar em animais em reuniao?",
    "q51": "Qual seria um desafio divertido envolvendo animais em reuniao?",
    "q52": "Qual seria um desafio serio envolvendo animais em reuniao?",
    "q53": "O que voce prefere manter simples quando o assunto e animais em reuniao?",
    "q54": "O que merece mais planejamento dentro de animais em reuniao?",
    "q55": "Que mito sobre animais em reuniao voce derrubaria hoje?",
    "q56": "Que qualidade humana aparece com forca em animais em reuniao?",
    "q57": "Que defeito humano aparece com frequencia em animais em reuniao?",
    "q58": "Que momento recente representa bem seu jeito de viver animais em reuniao?",
    "q59": "Como voce percebe que esta evoluindo em animais em reuniao?",
    "q60": "Que pergunta final fecharia uma conversa boa sobre animais em reuniao?"
  },
  "featured": false,
  "image": "deck-diversao-animais-em-reuniao"
}
