{
  "id": "relacionamentos-confianca-e-cuidado",
  "title": "Confianca e Cuidado",
  "description": "Como construir seguranca emocional de forma ativa.",
  "category": "Relacionamentos",
  "tags": [
    "confianca",
    "cuidado",
    "relacao",
    "colecao-relacionamentos",
    "serie-06"
  ],
  "questions": {
    "q1": "Qual momento marcou sua relacao com o tema confianca e cuidado?",
    "q2": "O que mais surpreende voce quando pensa em confianca e cuidado?",
    "q3": "Que lembranca sua combina demais com confianca e cuidado?",
    "q4": "Se voce tivesse que resumir confianca e cuidado em uma frase, qual seria?",
    "q5": "Qual lado pouco falado de confianca e cuidado mais chama sua atencao?",
    "q6": "Que experiencia boa voce associa imediatamente a confianca e cuidado?",
    "q7": "Que erro comum as pessoas cometem quando falam de confianca e cuidado?",
    "q8": "O que voce gostaria de viver mais dentro de confianca e cuidado?",
    "q9": "Qual conversa sincera sobre confianca e cuidado vale a pena ter mais vezes?",
    "q10": "Que habito ou atitude melhora muito qualquer experiencia ligada a confianca e cuidado?",
    "q11": "Quando confianca e cuidado funciona muito bem para voce?",
    "q12": "Quando confianca e cuidado fica mais dificil do que deveria?",
    "q13": "Que tipo de pessoa costuma combinar com o clima de confianca e cuidado?",
    "q14": "Que historia engraçada voce poderia contar sobre confianca e cuidado?",
    "q15": "Que historia profunda voce poderia contar sobre confianca e cuidado?",
    "q16": "Qual expectativa sobre confianca e cuidado voce ja mudou com o tempo?",
    "q17": "Que conselho sincero voce daria para alguem vivendo confianca e cuidado hoje?",
    "q18": "Que pergunta sobre confianca e cuidado quase ninguem faz e deveria fazer?",
    "q19": "O que faz voce confiar mais em alguem dentro de confianca e cuidado?",
    "q20": "O que faz voce perder o interesse em confianca e cuidado?",
    "q21": "Que detalhe simples torna confianca e cuidado melhor?",
    "q22": "Que exagero costuma atrapalhar confianca e cuidado?",
    "q23": "Se pudesse ajustar uma regra invisivel sobre confianca e cuidado, qual seria?",
    "q24": "Que sinal mostra que confianca e cuidado esta indo na direcao certa?",
    "q25": "Que sinal mostra que confianca e cuidado precisa ser revisto?",
    "q26": "Que aprendizado recente mudou sua visao sobre confianca e cuidado?",
    "q27": "Que dificuldade voce encara de forma mais leve hoje em confianca e cuidado?",
    "q28": "Qual escolha pequena gera grande impacto em confianca e cuidado?",
    "q29": "Se confianca e cuidado virasse um filme, que genero seria?",
    "q30": "Se confianca e cuidado tivesse trilha sonora, como ela seria?",
    "q31": "Que personagem real ou ficticio representaria bem confianca e cuidado?",
    "q32": "Qual parte de confianca e cuidado voce protege com mais cuidado?",
    "q33": "Qual parte de confianca e cuidado merece mais espontaneidade?",
    "q34": "Que limite faz bem quando o assunto e confianca e cuidado?",
    "q35": "Que risco vale a pena correr em confianca e cuidado?",
    "q36": "Que risco nao compensa correr em confianca e cuidado?",
    "q37": "O que seria uma versao mais madura de confianca e cuidado para voce?",
    "q38": "O que seria uma versao mais divertida de confianca e cuidado para voce?",
    "q39": "Que combinacao improvavel melhoraria confianca e cuidado?",
    "q40": "Que comparacao ajuda a explicar confianca e cuidado para outra pessoa?",
    "q41": "O que costuma ser mais importante do que parece em confianca e cuidado?",
    "q42": "O que costuma parecer importante e no fim nao e tanto em confianca e cuidado?",
    "q43": "Que memoria antiga ainda influencia sua visao sobre confianca e cuidado?",
    "q44": "Que desejo futuro aparece quando voce pensa em confianca e cuidado?",
    "q45": "O que voce faria diferente se pudesse recomecar em confianca e cuidado?",
    "q46": "O que vale repetir porque sempre funciona em confianca e cuidado?",
    "q47": "Que conversa pendente combinaria com o tema confianca e cuidado?",
    "q48": "Qual foi sua maior descoberta pessoal ligada a confianca e cuidado?",
    "q49": "Que atitude alheia faz voce admirar mais alguem em confianca e cuidado?",
    "q50": "Que atitude alheia faz voce se afastar em confianca e cuidado?",
    "q51": "Qual seria um desafio divertido envolvendo confianca e cuidado?",
    "q52": "Qual seria um desafio serio envolvendo confianca e cuidado?",
    "q53": "O que voce prefere manter simples quando o assunto e confianca e cuidado?",
    "q54": "O que merece mais planejamento dentro de confianca e cuidado?",
    "q55": "Que mito sobre confianca e cuidado voce derrubaria hoje?",
    "q56": "Que qualidade humana aparece com forca em confianca e cuidado?",
    "q57": "Que defeito humano aparece com frequencia em confianca e cuidado?",
    "q58": "Que momento recente representa bem seu jeito de viver confianca e cuidado?",
    "q59": "Como voce percebe que esta evoluindo em confianca e cuidado?",
    "q60": "Que pergunta final fecharia uma conversa boa sobre confianca e cuidado?"
  },
  "featured": false,
  "image": "deck-relacionamentos-confianca-e-cuidado"
}
